myscalekb_agent_base/__init__.py
myscalekb_agent_base/control_tags.py
myscalekb_agent_base/graph_builder.py
myscalekb_agent_base/myscale_query.py
myscalekb_agent_base/prompt.py
myscalekb_agent_base/retriever.py
myscalekb_agent_base/state.py
myscalekb_agent_base/sub_agent.py
myscalekb_agent_base/tool.py
myscalekb_agent_base/utils.py
myscalekb_agent_base/schemas/__init__.py
myscalekb_agent_base/schemas/agent_metadata.py
myscalekb_agent_base/schemas/knowledge_base.py
myscalekb_agent_base/schemas/message.py
originhub_myscalekb_agent_base-0.2.0.dist-info/METADATA
originhub_myscalekb_agent_base-0.2.0.dist-info/WHEEL
originhub_myscalekb_agent_base-0.2.0.dist-info/top_level.txt
originhub_myscalekb_agent_base-0.2.0.dist-info/RECORD
