Metadata-Version: 2.4
Name: originhub-myscalekb-agent-base
Version: 0.2.0
Summary: Base classes for MyScaleKB Agent APP
Home-page: https://github.com/myscale/myscalekb-agent-base
Author: louh
Author-email: louh@originhub.tech
Classifier: Development Status :: 3 - Alpha
Classifier: Intended Audience :: Developers
Classifier: License :: OSI Approved :: MIT License
Classifier: Programming Language :: Python :: 3.12
Requires-Python: >=3.12
Requires-Dist: pydantic~=2.8.2
Requires-Dist: langchain==0.3.19
Requires-Dist: langchain-openai==0.3.7
Requires-Dist: langchain-community==0.3.18
Requires-Dist: langgraph==0.2.35
Requires-Dist: nanoid~=2.0.0
Requires-Dist: clickhouse-connect~=0.7.18
Requires-Dist: json5~=0.9.25
Requires-Dist: json_repair~=0.30.0
Dynamic: author
Dynamic: author-email
Dynamic: classifier
Dynamic: description
Dynamic: description-content-type
Dynamic: home-page
Dynamic: requires-dist
Dynamic: requires-python
Dynamic: summary
